pyxnat/__init__.py
pyxnat/version.py
pyxnat/core/__init__.py
pyxnat/core/array.py
pyxnat/core/attributes.py
pyxnat/core/cache.py
pyxnat/core/downloadutils.py
pyxnat/core/errors.py
pyxnat/core/help.py
pyxnat/core/httputil.py
pyxnat/core/interfaces.py
pyxnat/core/jsonutil.py
pyxnat/core/manage.py
pyxnat/core/pathutil.py
pyxnat/core/pipelines.py
pyxnat/core/provenance.py
pyxnat/core/resources.py
pyxnat/core/schema.py
pyxnat/core/search.py
pyxnat/core/select.py
pyxnat/core/tags.py
pyxnat/core/uriutil.py
pyxnat/core/users.py
pyxnat/core/xpass.py
pyxnat/core/xpath_store.py
pyxnat/tests/__init__.py
pyxnat/tests/attributes_test.py
pyxnat/tests/custom_variables_test.py
pyxnat/tests/experiments_tests.py
pyxnat/tests/hello_again.txt
pyxnat/tests/hello_xnat.txt
pyxnat/tests/interfaces_test.py
pyxnat/tests/jsonutil_test.py
pyxnat/tests/manage_test.py
pyxnat/tests/provenance_test.py
pyxnat/tests/resources_test.py
pyxnat/tests/results.csv
pyxnat/tests/scans_tests.py
pyxnat/tests/search_test.py
pyxnat/tests/select_test.py
pyxnat/tests/uriutil_test.py
pyxnat/tests/user_and_project_management_test.py
pyxnat/tests/xpass_test.py
pyxnat/tests/xpath_test.py
pyxnat_ldax-1.0.0.0.7.dist-info/METADATA
pyxnat_ldax-1.0.0.0.7.dist-info/WHEEL
pyxnat_ldax-1.0.0.0.7.dist-info/top_level.txt
pyxnat_ldax-1.0.0.0.7.dist-info/RECORD
