Metadata-Version: 2.1
Name: pyxnat-ldax
Version: 1.0.0.0.7
Summary: Xnat in Python
Home-page: https://github.com/VUIIS/pyxnat
Author: Shunxing Bao
Author-email: onealbao@gmail.com
License: BSD
Platform: any
Classifier: Development Status :: 4 - Beta
Classifier: Environment :: Console
Classifier: Intended Audience :: Developers
Classifier: Intended Audience :: Science/Research
Classifier: Intended Audience :: Education
Classifier: License :: OSI Approved :: BSD License
Classifier: Operating System :: OS Independent
Classifier: Programming Language :: Python
Classifier: Topic :: Scientific/Engineering
Classifier: Topic :: Utilities
Classifier: Topic :: Internet :: WWW/HTTP
Requires: requests
Requires-Dist: requests
Requires-Dist: lxml
Requires-Dist: requests[security]
